mokka/__init__.py
mokka/channels/__init__.py
mokka/channels/torch.py
mokka/e2e/__init__.py
mokka/e2e/torch.py
mokka/equalizers/__init__.py
mokka/equalizers/adaptive/__init__.py
mokka/equalizers/adaptive/torch.py
mokka/equalizers/torch.py
mokka/functional/__init__.py
mokka/functional/torch.py
mokka/inft/__init__.py
mokka/inft/torch.py
mokka/mapping/__init__.py
mokka/mapping/numpy.py
mokka/mapping/torch.py
mokka/normalization/__init__.py
mokka/normalization/torch.py
mokka/pulseshaping/__init__.py
mokka/pulseshaping/torch.py
mokka/synchronizers/__init__.py
mokka/synchronizers/phase/__init__.py
mokka/synchronizers/phase/torch/__init__.py
mokka/synchronizers/phase/torch/bps.py
mokka/synchronizers/phase/torch/cycleslip_comp.py
mokka/synchronizers/phase/torch/pilot.py
mokka/synchronizers/phase/torch/vandv.py
mokka/utils/__init__.py
mokka/utils/bitops/__init__.py
mokka/utils/bitops/numpy.py
mokka/utils/bitops/torch.py
mokka/utils/decorators.py
mokka/utils/generators/__init__.py
mokka/utils/generators/numpy.py
mokka/utils/generators/torch.py
mokka-1.1.0.dist-info/WHEEL
mokka-1.1.0.dist-info/METADATA
mokka-1.1.0.dist-info/RECORD
