Metadata-Version: 2.3
Name: mokka
Version: 1.1.0
Summary: A machine learning toolbox for communications engineering
Keywords: communications engineering,machine learning
Author: Andrej Rode, Shrinivas Chimmalgi, Benedikt Geiger, Laurent Schmalen
Author-email: Andrej Rode <rode@kit.edu>, Shrinivas Chimmalgi <shrinivas.chimmalgi@kit.edu>, Benedikt Geiger <benedikt.geiger@kit.edu>, Laurent Schmalen <laurent.schmalen@kit.edu>
License: Apache-2.0
Requires-Dist: attrs>=23.2.0,<24.0.0
Requires-Dist: numpy>=1.26.4,<2.0.0
Requires-Dist: torch>=2.5.1,<3.0.0
Requires-Dist: torchaudio>=2.5.1,<3.0.0
Requires-Dist: matplotlib>=3.9.2,<4.0.0
Requires-Dist: scipy>=1.13.1,<2.0.0
Requires-Dist: pyqtgraph>=0.13.7,<1.0.0
Requires-Dist: jaxtyping>=0.2.36,<1.0.0
Requires-Dist: wandb ; extra == 'remotelog'
Requires-Dist: sionna ; extra == 'tf'
Maintainer: Andrej Rode, Shrinivas Chimmalgi, Benedikt Geiger
Maintainer-email: Andrej Rode <rode@kit.edu>, Shrinivas Chimmalgi <shrinivas.chimmalgi@kit.edu>, Benedikt Geiger <benedikt.geiger@kit.edu>
Requires-Python: >=3.10, <4.0
Provides-Extra: remotelog
Provides-Extra: tf
